[
 {
   "A": "땅 번호",
   "B": "이름",
   "C": "유형 번호"
 },
 {
   "A": "1",
   "B": "출발",
   "C": "3"
 },
 {
   "A": "2",
   "B": "타이페이",
   "C": "1"
 },
 {
   "A": "3",
   "B": "황금열쇠",
   "C": "3"
 },
 {
   "A": "4",
   "B": "베이징",
   "C": "1"
 },
 {
   "A": "5",
   "B": "마닐라",
   "C": "1"
 },
 {
   "A": "6",
   "B": "제주",
   "C": "2"
 },
 {
   "A": "7",
   "B": "싱가포르",
   "C": "1"
 },
 {
   "A": "8",
   "B": "황금열쇠",
   "C": "3"
 },
 {
   "A": "9",
   "B": "카이로",
   "C": "1"
 },
 {
   "A": "10",
   "B": "이스탄불",
   "C": "1"
 },
 {
   "A": "11",
   "B": "무인도",
   "C": "3"
 },
 {
   "A": "12",
   "B": "아테네",
   "C": "1"
 },
 {
   "A": "13",
   "B": "황금열쇠",
   "C": "3"
 },
 {
   "A": "14",
   "B": "코펜하겐",
   "C": "1"
 },
 {
   "A": "15",
   "B": "스톡홀롬",
   "C": "1"
 },
 {
   "A": "16",
   "B": "콩코드여객기",
   "C": "2"
 },
 {
   "A": "17",
   "B": "베른",
   "C": "1"
 },
 {
   "A": "18",
   "B": "황금열쇠",
   "C": "3"
 },
 {
   "A": "19",
   "B": "베를린",
   "C": "1"
 },
 {
   "A": "20",
   "B": "오타와",
   "C": "1"
 },
 {
   "A": "21",
   "B": "사회복지기금 회수",
   "C": "3"
 },
 {
   "A": "22",
   "B": "부에노스아이레스",
   "C": "1"
 },
 {
   "A": "23",
   "B": "황금열쇠",
   "C": "3"
 },
 {
   "A": "24",
   "B": "상파울로",
   "C": "1"
 },
 {
   "A": "25",
   "B": "시드니",
   "C": "1"
 },
 {
   "A": "26",
   "B": "부산",
   "C": "2"
 },
 {
   "A": "27",
   "B": "하와이",
   "C": "1"
 },
 {
   "A": "28",
   "B": "리스본",
   "C": "1"
 },
 {
   "A": "29",
   "B": "퀸 엘리자베스호",
   "C": "2"
 },
 {
   "A": "30",
   "B": "마드리드",
   "C": "1"
 },
 {
   "A": "31",
   "B": "우주여행",
   "C": "3"
 },
 {
   "A": "32",
   "B": "도쿄",
   "C": "1"
 },
 {
   "A": "33",
   "B": "컬럼비아호",
   "C": "3"
 },
 {
   "A": "34",
   "B": "파리",
   "C": "1"
 },
 {
   "A": "35",
   "B": "로마",
   "C": "1"
 },
 {
   "A": "36",
   "B": "황금열쇠",
   "C": "3"
 },
 {
   "A": "37",
   "B": "런던",
   "C": "1"
 },
 {
   "A": "38",
   "B": "뉴욕",
   "C": "1"
 },
 {
   "A": "39",
   "B": "사회복지기금 기부",
   "C": "3"
 },
 {
   "A": "40",
   "B": "서울",
   "C": "2"
 }
]